management/__init__.py
management/commands/__init__.py
management/commands/view_genrator.py
first_django_generator-0.3.3.dist-info/LICENSE
first_django_generator-0.3.3.dist-info/METADATA
first_django_generator-0.3.3.dist-info/WHEEL
first_django_generator-0.3.3.dist-info/entry_points.txt
first_django_generator-0.3.3.dist-info/top_level.txt
first_django_generator-0.3.3.dist-info/RECORD
