Metadata-Version: 2.1
Name: first-django-generator
Version: 0.3.3
Summary: A Django management command to generate views and serializers based on models.
Home-page: https://github.com/yourusername/my_django_generator
Author: Saurabh Shinde
Author-email: saurabh004shinde@gmail.com
Classifier: Development Status :: 4 - Beta
Classifier: Intended Audience :: Developers
Classifier: License :: OSI Approved :: MIT License
Classifier: Programming Language :: Python :: 3
Classifier: Framework :: Django
License-File: LICENSE
Requires-Dist: django >=3.0
